make4db/provider.py
make4db_api-0.1.2.dist-info/METADATA
make4db_api-0.1.2.dist-info/WHEEL
make4db_api-0.1.2.dist-info/top_level.txt
make4db_api-0.1.2.dist-info/RECORD
