Metadata-Version: 2.4
Name: make4db-api
Version: 0.1.2
Summary: API for providers of make4db tool
Author-email: Paresh Adhia <padhia+github@gmail.com>
Classifier: Programming Language :: Python :: 3
Requires-Python: >=3.11
